{
    "name": "QueryCommon10",
    "fields": [
        {
            "fieldName": "queryName",
            "fieldType": "String",
            "fieldValidateRules": [
                "maxlength"
            ],
            "fieldValidateRulesMaxlength": 256
        },
        {
            "fieldName": "queryDate",
            "fieldType": "Instant"
        },
        {
            "fieldName": "queryUser",
            "fieldType": "String",
            "fieldValidateRules": [
                "maxlength"
            ],
            "fieldValidateRulesMaxlength": 256
        },
        {
            "fieldName": "col01",
            "fieldType": "String",
            "fieldValidateRules": [
                "maxlength"
            ],
            "fieldValidateRulesMaxlength": 4000
        },
        {
            "fieldName": "col02",
            "fieldType": "String",
            "fieldValidateRules": [
                "maxlength"
            ],
            "fieldValidateRulesMaxlength": 4000
        },
        {
            "fieldName": "col03",
            "fieldType": "String",
            "fieldValidateRules": [
                "maxlength"
            ],
            "fieldValidateRulesMaxlength": 4000
        },
        {
            "fieldName": "col04",
            "fieldType": "String",
            "fieldValidateRules": [
                "maxlength"
            ],
            "fieldValidateRulesMaxlength": 4000
        },
        {
            "fieldName": "col05",
            "fieldType": "String",
            "fieldValidateRules": [
                "maxlength"
            ],
            "fieldValidateRulesMaxlength": 4000
        },
        {
            "fieldName": "col06",
            "fieldType": "String",
            "fieldValidateRules": [
                "maxlength"
            ],
            "fieldValidateRulesMaxlength": 4000
        },
        {
            "fieldName": "col07",
            "fieldType": "String",
            "fieldValidateRules": [
                "maxlength"
            ],
            "fieldValidateRulesMaxlength": 4000
        },
        {
            "fieldName": "col08",
            "fieldType": "String",
            "fieldValidateRules": [
                "maxlength"
            ],
            "fieldValidateRulesMaxlength": 4000
        },
        {
            "fieldName": "col09",
            "fieldType": "String",
            "fieldValidateRules": [
                "maxlength"
            ],
            "fieldValidateRulesMaxlength": 4000
        },
        {
            "fieldName": "col10",
            "fieldType": "String",
            "fieldValidateRules": [
                "maxlength"
            ],
            "fieldValidateRulesMaxlength": 4000
        }
    ],
    "relationships": [],
    "changelogDate": "20190128074858",
    "javadoc": "QueryCommon10 通用查询10\n@author JungleYang.",
    "entityTableName": "query_common_10",
    "dto": "mapstruct",
    "pagination": "infinite-scroll",
    "service": "serviceImpl",
    "jpaMetamodelFiltering": true,
    "fluentMethods": true,
    "clientRootFolder": "",
    "applications": "*",
    "angularJSSuffix": "sdmSuffix"
}